[{"credentialType":"Diploma","credentialTitle":"Accounting and Finance","programAttribute":"Business","programDetail":"Neque porro quisquam est qui dolorem ipsum quia dolor sit amet, consectetur, adipisci velit...","calendarYear":"2022/23","academicYear":"2022/23","credit":"60","gradGPA":"3.0","programMarketingTitle":"Program Marketing Title","admissionGPA1":"2.75","admissionGPA2":"2.75","facultyArea":"Business and Management","departmentArea":"Accounting","discipline":"Accounting","psiProgramCode":"XX000","psiUrl":"Program URL displays here","cip":"123","cipModified":"123","epbcProgramTitle":"EPBC Program Title","epbcProgramId":"123","psipsCode":"123","institutionId":1439,"institutionName":"College of New Caledonia","state":"Published","id":1},{"credentialType":"Bachelor of Commerce","credentialTitle":"Accounting","programAttribute":"Business","programDetail":"Neque porro quisquam est qui dolorem ipsum quia dolor sit amet, consectetur, adipisci velit...","calendarYear":"2022/23","academicYear":"2022/23","credit":"120","gradGPA":"3.0","programMarketingTitle":"Program Marketing Title","admissionGPA1":"2.75","admissionGPA2":"2.75","facultyArea":"Business","departmentArea":"Commerce","discipline":"Accounting","psiProgramCode":"XX000","psiUrl":"Program URL displays here","cip":"52","cipModified":"123","epbcProgramTitle":"EPBC Program Title","epbcProgramId":"123","psipsCode":"1","institutionId":7747,"institutionName":"University of Northern British Columbia","state":"Published","id":2}]
